{
  "$FFFF0000": 19,
  "$FFFFD0E0": 9,
  "$FFFF8000": 7,
  "$FFFFFFFF": 4,
  "$FFFF0100": 3,
  "$FFFFE002": 2,
  "$FFFFC32C": 2,
  "$FFFFC340": 2,
  "$FFFFC7F2": 2,
  "$FFFFC7F0": 2,
  "$FFFFC60D": 2,
  "$FFFF1500": 2,
  "$FFFF4200": 2,
  "$FFFF1800": 2,
  "$FFFF3A00": 2,
  "$FFFF9000": 2,
  "$FFFFC170": 2,
  "$FFFFC0FC": 2,
  "$FFFFC7C0": 2,
  "$FFFFC768": 2,
  "$FFFFC767": 2,
  "$FFFFC7AC": 2,
  "$FFFFC7AB": 2,
  "$FFFFC746": 2,
  "$FFFFC762": 2,
  "$FFFFC78B": 2,
  "$FFFFC76A": 2,
  "$FFFFC765": 2,
  "$FFFFC786": 2,
  "$FFFFC736": 2,
  "$FFFFC764": 2,
  "$FFFFC761": 2,
  "$FFFFC74E": 2,
  "$FFFFC772": 2,
  "$FFFFC74C": 2,
  "$FFFFC771": 2,
  "$FFFFC74A": 2,
  "$FFFFC770": 2,
  "$FFFFC81D": 2,
  "$FFFFC753": 2,
  "$FFFFC77B": 2,
  "$FFFFC759": 2,
  "$FFFFC784": 2,
  "$FFFFC766": 2,
  "$FFFFC57C": 2,
  "$FFFFC76D": 2,
  "$FFFFC76E": 2,
  "$FFFFC76F": 2,
  "$FFFFC774": 2,
  "$FFFFC776": 2,
  "$FFFFC775": 2,
  "$FFFFC777": 2,
  "$FFFFE200": 2,
  "$FFFFE400": 2,
  "$FFFFA200": 2,
  "$FFFFC0A0": 2,
  "$FFFFC20C": 2,
  "$FFFFC240": 2,
  "$FFFF7F4C": 2,
  "$FFFF820A": 2,
  "$FFFF85D0": 2,
  "$FFFF88C4": 2,
  "$FFFF8C8A": 2,
  "$FFFF8366": 2,
  "$FFFF83FE": 2,
  "$FFFF82AA": 2,
  "$FFFF7E80": 2,
  "$FFFFC0BD": 2,
  "$FFFFC10A": 2,
  "$FFFFC108": 2,
  "$FFFFC09A": 2,
  "$FFFFC09C": 2,
  "$FFFFC09E": 2,
  "$FFFF4D84": 2,
  "$FFFF6384": 2,
  "$FFFFC3A4": 2,
  "$FFFFC646": 2,
  "$FFFFC77E": 2,
  "$FFFFC4AC": 2,
  "$FFFFC7C3": 2,
  "$FFFFC7C5": 2,
  "$FFFFC72A": 2,
  "$FFFFC798": 2,
  "$FFFFC7A7": 2,
  "$FFFFC7A8": 2,
  "$FFFFFE00": 1,
  "$FFFFC3F0": 1,
  "$FFFFD000": 1,
  "$FFFFCC00": 1,
  "$FFFFCC04": 1,
  "$FFFFCC74": 1,
  "$FFFFC0FF": 1,
  "$FFFFC614": 1,
  "$FFFF9010": 1,
  "$FFFF9020": 1,
  "$FFFF9300": 1,
  "$FFFF9320": 1,
  "$FFFF9600": 1,
  "$FFFF9610": 1,
  "$FFFF9620": 1,
  "$FFFFC7AA": 1,
  "$FFFFC779": 1,
  "$FFFFC77A": 1,
  "$FFFFC73F": 1,
  "$FFFFC740": 1,
  "$FFFFC742": 1,
  "$FFFFC785": 1,
  "$FFFFC747": 1,
  "$FFFFC783": 1,
  "$FFFFCC50": 1,
  "$FFFFC804": 1,
  "$FFFFC7ED": 1,
  "$FFFFC81B": 1,
  "$FFFFC80D": 1,
  "$FFFFE3F0": 1,
  "$FFFF3600": 1,
  "$FFFFC65B": 1,
  "$FFFFC65C": 1,
  "$FFFFC65D": 1,
  "$FFFFC701": 1,
  "$FFFFC35E": 1,
  "$FFFF4D80": 1,
  "$FFFFC118": 1,
  "$FFFFC3B2": 1,
  "$FFFFC254": 1,
  "$FFFFC756": 1,
  "$FFFFC7C2": 1,
  "$FFFFC79A": 1,
  "$FFFFC788": 1,
  "$FFFFC79B": 1,
  "$FFFFC7BA": 1,
  "$FFFFC7BC": 1,
  "$FFFFC7AE": 1,
  "$FFFFC7AF": 1,
  "$FFFFC789": 1,
  "$FFFFC78A": 1,
  "$FFFFC78F": 1,
  "$FFFFC799": 1,
  "$FFFFC79C": 1,
  "$FFFFC7B0": 1,
  "$FFFFC7B2": 1,
  "$FFFFC7BE": 1,
  "$FFFFC7BF": 1,
  "$FFFFC7EE": 1,
  "$FFFFC7E0": 1,
  "$FFFFC7EC": 1,
  "$FFFFC7E1": 1,
  "$FFFFC7E3": 1,
  "$FFFFC7EF": 1,
  "$FFFFC7E6": 1,
  "$FFFFC7EA": 1,
  "$FFFFC78D": 1,
  "$FFFFC78C": 1,
  "$FFFFC790": 1,
  "$FFFFC791": 1,
  "$FFFFC793": 1,
  "$FFFFC796": 1,
  "$FFFFC79E": 1,
  "$FFFFC7E8": 1,
  "$FFFFC7A2": 1,
  "$FFFFC787": 1,
  "$FFFFC7A4": 1,
  "$FFFFC7A5": 1,
  "$FFFFC73E": 1,
  "$FFFFC769": 1,
  "$FFFFC7A9": 1,
  "$FFFFC805": 1,
  "$FFFFC806": 1,
  "$FFFFC807": 1,
  "$FFFFC780": 1,
  "$FFFFC781": 1,
  "$FFFFC81E": 1,
  "$FFFFC782": 1,
  "$FFFFC81F": 1,
  "$FFFFC7C1": 1,
  "$FFFFC77F": 1,
  "$FFFFF989": 1,
  "$FFFFF909": 1,
  "$FFFFF001": 1,
  "$FFFF6000": 1,
  "$FFFF319C": 1,
  "$FFFF0414": 1,
  "$FFFF0443": 1,
  "$FFFF3333": 1,
  "$FFFF3355": 1,
  "$FFFF3353": 1,
  "$FFFFFCCC": 1,
  "$FFFFF311": 1
}